README.rst
setup.py
aiowerkzeug/__init__.py
aiowerkzeug/_reloader.py
aiowerkzeug/local.py
aiowerkzeug/serving.py
aiowerkzeug.egg-info/PKG-INFO
aiowerkzeug.egg-info/SOURCES.txt
aiowerkzeug.egg-info/dependency_links.txt
aiowerkzeug.egg-info/requires.txt
aiowerkzeug.egg-info/top_level.txt
aiowerkzeug.egg-info/zip-safe