Metadata-Version: 1.1
Name: aiowerkzeug
Version: 0.1.2
Summary: Werkzeug for asyncio
Home-page: https://github.com/alfred82santa/aiowerkzeug
Author: alfred82santa
Author-email: alfred82santa@gmail.com
License: UNKNOWN
Platform: UNKNOWN
Classifier: Intended Audience :: Developers
Classifier: Programming Language :: Python
Classifier: Programming Language :: Python :: 3.5
Classifier: Programming Language :: Python :: 3.4
Classifier: License :: OSI Approved :: MIT License
Classifier: Development Status :: 3 - Alpha
